Workbook

Sheet Overview
B2: ATM Map prospecting cost model
B3: A planning model for screening 2,500 unique sites: compare the prior manual list-building baseline with the market-calibrated ATM Map workflow, test uncertainty, and track campaign outcomes.
B5: BASE PLANNING SCENARIO
B6: SCOPE | D6: MANUAL BASELINE | F6: ATM MAP WORKFLOW | H6: GROSS API COST
B7: ='Funnel & cost'!C7 -> 2500 | D7: ='Funnel & cost'!C28 -> 187.5 | F7: ='Funnel & cost'!D28 -> 50.288333 | H7: ='Funnel & cost'!D32 -> 10.85
B8: unique sites screened | D8: estimated analyst hours | F8: estimated analyst hours | H8: before monthly free usage
B10: DECISION VIEW
B11: METRIC | D11: MANUAL BASELINE | F11: ATM MAP WORKFLOW | H11: PLANNING INTERPRETATION
B12: Analyst hours | D12: ='Funnel & cost'!C28 -> 187.5 | F12: ='Funnel & cost'!D28 -> 50.288333 | H12: End-to-end effort for the same screening target.
B13: List-production cost | D13: ='Funnel & cost'!C36 -> 6375 | F13: ='Funnel & cost'!D36 -> 1720.6533 | H13: Labor plus API usage in the ATM Map column.
B14: Cost per unique site | D14: ='Funnel & cost'!C37 -> 2.55 | F14: ='Funnel & cost'!D37 -> 0.68826133 | H14: A common unit for comparing workflow efficiency.
B15: Estimated mail-ready sites | D15: ='Funnel & cost'!C18 -> 1774 | F15: ='Funnel & cost'!D18 -> 1774 | H15: Ready records plus review-needed records that pass.
B17: WHAT THIS MODEL SUPPORTS | F17: HOW TO REVIEW
B18: Use the model to set a list-production budget, compare workflow capacity, and see which assumptions materially change the result. The base case includes search setup, review, exception handling, reconciliation, QA, overhead, and API usage. | F18: 1 | G18: Change yellow cells on Assumptions for a new planning case.
F19: 2 | G19: Review Funnel & cost for the base workflow and Sensitivity for the range.
F20: 3 | G20: Use Outcome plan after a campaign closes to calculate response, conversion, and CAC.
F21: 4 | G21: Use the remaining tabs for source, validation, pivot, chart, and formula detail.
B23: MODEL MAP
B24: Funnel & cost | D24: Market-calibrated screening, labor, API, and unit-cost model.
B25: Assumptions | D25: Editable scenario inputs and linked operating benchmarks.
B26: Sensitivity | D26: High-, base-, and low-effort ranges plus a two-way table.
B27: Outcome plan | D27: Closed-campaign inputs for response, conversion, and total CAC.
B28: Supporting tabs | D28: Sources, completed-run evidence, PivotTable, charts, and model checks.
B30: Planning use: compare capacity and cost before a run. Use Outcome plan to record closed-campaign results.

Sheet Funnel & cost
B2: ATM Map workflow · market-calibrated planning scenario
B3: Compares the prior manual list-building baseline with the ATM Map workflow for the same target, using the completed 21-area market run for search yield and qualification mix.
B5: METRIC | C5: MANUAL BASELINE | D5: ATM MAP WORKFLOW | E5: UNIT | F5: PLANNING NOTE
B6: SITE FUNNEL
B7: Target unique physical sites screened | C7: =Assumptions!C6 -> 2500 | D7: =Assumptions!C6 -> 2500 | E7: sites | F7: Common decision unit; screening does not automatically make a site outreach-ready.
B8: Place-ID yield per completed area | D8: =Assumptions!C12*(1-Assumptions!C17) -> 88.380952 | E8: primary Place IDs/area | F8: Observed mapped yield adjusted by the measured cross-area repeat rate.
B9: Completed areas required | D9: =ROUNDUP(D7/D8,0) -> 29 | E9: whole searches | F9: Areas are rounded up to cover the target.
B10: Gross candidate observations | D10: =D9*Assumptions!C12 -> 2708.0476 | E10: observations | F10: Before cross-area repeat observations are removed.
B11: Estimated repeated Place-ID observations | D11: =D10*Assumptions!C17 -> 145 | E11: Place-ID observations | F11: Uses the repeat rate measured across neighboring search areas.
B12: Estimated unique returned primary Place IDs after overlap | D12: =D10-D11 -> 2563.0476 | E12: primary Place IDs | F12: Planning proxy for the physical-site target; reconcile records before treating them as distinct sites.
B13: Additional candidate records held for later | D13: =MAX(0,D12-D7) -> 63.047619 | E13: primary Place IDs | F13: Whole areas can return more candidate records than the current cycle needs.
B14: Ready for outreach | C14: =ROUND(C7*Assumptions!C14,0) -> 1467 | D14: =ROUND(D7*Assumptions!C14,0) -> 1467 | E14: sites | F14: Estimated from the current qualification mix.
B15: Review needed | C15: =ROUND(C7*Assumptions!C15,0) -> 614 | D15: =ROUND(D7*Assumptions!C15,0) -> 614 | E15: sites | F15: Records requiring a human check before outreach.
B16: Not currently viable | C16: =C7-C14-C15 -> 419 | D16: =D7-D14-D15 -> 419 | E16: sites | F16: Remaining records after Ready and Review needed.
B17: Review-needed sites that pass | C17: =ROUND(C15*Assumptions!C18,0) -> 307 | D17: =ROUND(D15*Assumptions!C18,0) -> 307 | E17: sites | F17: Share expected to become outreach-ready after review.
B18: Estimated mail-ready sites | C18: =C14+C17 -> 1774 | D18: =D14+D17 -> 1774 | E18: sites | F18: Ready records plus review-needed records that pass.
B19: Funnel check | C19: =SUM(C14:C16) -> 2500 | D19: =SUM(D14:D16) -> 2500 | E19: sites | F19: Ready, Review needed, and Not currently viable must equal the target.
B20: WORKFLOW EFFORT
B21: Search setup and monitoring | C21: 0 | D21: =D9*Assumptions!C22 -> 87 | E21: minutes | F21: Area selection and monitoring for each completed search.
B22: Review of each unique site | C22: =C7*Assumptions!C9 -> 11250 | D22: =D7*Assumptions!C20/60 -> 1250 | E22: minutes | F22: Manual baseline uses prior target/time; ATM Map includes review of every candidate.
B23: Additional review for flagged sites | C23: 0 | D23: =D15*Assumptions!C21 -> 1228 | E23: minutes | F23: Applied to every record marked Review needed.
B24: Reconciliation and export | C24: 0 | D24: =D9*Assumptions!C23 -> 58 | E24: minutes | F24: Cross-search review and controlled export.
B25: Batch QA and administration | C25: 0 | D25: =Assumptions!C24*60 -> 120 | E25: minutes | F25: Final checks, handoff, and exception administration.
B26: Direct workflow minutes | C26: =SUM(C21:C25) -> 11250 | D26: =SUM(D21:D25) -> 2743 | E26: minutes | F26: Subtotal before overhead.
B27: Workflow overhead | C27: 0 | D27: =D26*Assumptions!C25 -> 274.3 | E27: minutes | F27: Allowance for coordination, rework, and interruptions.
B28: Estimated analyst hours | C28: =(C26+C27)/60 -> 187.5 | D28: =(D26+D27)/60 -> 50.288333 | E28: hours | F28: All modeled effort components.
B29: Estimated labor cost | C29: =C28*Assumptions!C10 -> 6375 | D29: =D28*Assumptions!C10 -> 1709.8033 | F29: Uses the editable loaded hourly rate.
B30: API AND TOTAL COST
B31: Paid API calls | C31: 0 | D31: =ROUNDUP(D9*Assumptions!C13,0) -> 310 | E31: whole calls | F31: Observed calls per area, rounded up for planning.
B32: Gross API cost | C32: 0 | D32: =D31*Assumptions!C27/1000 -> 10.85 | F32: Shown before any monthly free usage is allocated.
B33: Monthly free events allocated | C33: 0 | D33: =MIN(D31,Assumptions!C28*Assumptions!C29) -> 0 | E33: events | F33: Defaults to zero; allocate only when available to this planning cycle.
B34: Allocated free-usage credit | C34: 0 | D34: =D33*Assumptions!C27/1000 -> 0 | F34: Shown separately from gross API cost.
B35: Net API cost | C35: 0 | D35: =MAX(0,D32-D34) -> 10.85 | F35: Gross API cost less any explicit allocation.
B36: TOTAL PLANNED LIST-PRODUCTION COST | C36: =C29 -> 6375 | D36: =D29+D35 -> 1720.6533 | F36: Labor plus net API cost.
B37: Cost per unique site screened | C37: =C36/C7 -> 2.55 | D37: =D36/D7 -> 0.68826133 | F37: Common unit for comparing workflow efficiency.
B38: Cost per estimated mail-ready site | C38: =C36/C18 -> 3.5935738 | D38: =D36/D18 -> 0.9699286 | F38: Depends on qualification mix and review pass rate.
B39: Planning difference vs manual baseline | C39: =C36-D36 -> 4654.3467 | F39: Capacity and budget difference between the two planning baselines.

Sheet Assumptions
B2: Planning inputs
B3: Yellow cells are editable scenario inputs. Blue cells link to the source register; gray cells are formulas used throughout the workbook.
B5: INPUT | C5: VALUE | D5: UNIT | E5: INPUT TYPE | F5: SOURCE / CALCULATION | G5: PLANNING NOTE
B6: Target unique physical sites screened | C6: 2500 | D6: unique sites | E6: Scenario input | F6: editable input | G6: Volume for one list-production cycle.
B7: Manual activity target | C7: =INDEX('Source register'!$D$6:$D$31,MATCH("manual_target_per_day",'Source register'!$B$6:$B$31,0)) -> 40 | D7: sites/day | E7: Operating baseline | F7: manual_target_per_day | G7: Prior daily list-building target.
B8: Manual prospecting time | C8: =INDEX('Source register'!$D$6:$D$31,MATCH("manual_hours_per_day",'Source register'!$B$6:$B$31,0)) -> 3 | D8: hours/day | E8: Operating baseline | F8: manual_hours_per_day | G8: Time assigned to manual prospecting.
B9: Manual minutes per site | C9: =C8*60/C7 -> 4.5 | D9: minutes/site | E9: Formula | F9: time ÷ target | G9: Daily prospecting time ÷ daily target.
B10: Analyst loaded cost | C10: 34 | D10: $/hour | E10: Scenario input | F10: editable input | G10: Planning rate; replace with the employer standard when available.
B11: MAP YIELD AND QUALIFICATION
B12: Mapped observations per completed area | C12: =INDEX('Source register'!$D$6:$D$31,MATCH("val_results_per_search",'Source register'!$B$6:$B$31,0)) -> 93.380952 | D12: observations/area | E12: Completed market run | F12: val_results_per_search | G12: Average across 21 completed Los Angeles grid areas.
B13: API calls per completed area | C13: =INDEX('Source register'!$D$6:$D$31,MATCH("val_calls_per_search",'Source register'!$B$6:$B$31,0)) -> 10.666667 | D13: calls/area | E13: Completed market run | F13: val_calls_per_search | G13: Observed average; total planned calls are rounded up.
B14: Ready share | C14: =INDEX('Source register'!$D$6:$D$31,MATCH("val_ready_count",'Source register'!$B$6:$B$31,0))/INDEX('Source register'!$D$6:$D$31,MATCH("val_bucket_total",'Source register'!$B$6:$B$31,0)) -> 0.58674569 | D14: share | E14: Formula | F14: 1089 / 1856 | G14: Ready share across the completed market run.
B15: Review-needed share | C15: =INDEX('Source register'!$D$6:$D$31,MATCH("val_verify_count",'Source register'!$B$6:$B$31,0))/INDEX('Source register'!$D$6:$D$31,MATCH("val_bucket_total",'Source register'!$B$6:$B$31,0)) -> 0.24568966 | D15: share | E15: Formula | F15: 456 / 1856 | G15: Review-needed share across the completed market run.
B16: Not-currently-viable share | C16: =INDEX('Source register'!$D$6:$D$31,MATCH("val_not_viable_count",'Source register'!$B$6:$B$31,0))/INDEX('Source register'!$D$6:$D$31,MATCH("val_bucket_total",'Source register'!$B$6:$B$31,0)) -> 0.16756466 | D16: share | E16: Formula | F16: 311 / 1856 | G16: Not-currently-viable share across the completed market run.
B17: Cross-search duplicate / overlap rate | C17: =INDEX('Source register'!$D$6:$D$31,MATCH("val_overlap_rate",'Source register'!$B$6:$B$31,0)) -> 0.05354411 | D17: share | E17: Completed market run | F17: val_overlap_rate | G17: Observed repeats across neighboring market-search areas.
B18: Review-needed pass rate | C18: 0.5 | D18: share | E18: Scenario input | F18: editable input | G18: Share of Review-needed records expected to become outreach-ready.
B19: WORKFLOW EFFORT
B20: Base review time for every unique site | C20: 30 | D20: seconds/site | E20: Scenario input | F20: editable input | G20: Initial review of each unique mapped candidate.
B21: Additional review for Review needed | C21: 2 | D21: minutes/flagged site | E21: Scenario input | F21: editable input | G21: Extra time for each Review-needed record.
B22: Search setup / monitoring | C22: 3 | D22: minutes/search | E22: Scenario input | F22: editable input | G22: Area selection and run monitoring.
B23: Reconciliation and export | C23: 2 | D23: minutes/search | E23: Scenario input | F23: editable input | G23: Cross-search review and controlled export.
B24: Batch QA / administration | C24: 2 | D24: hours/batch | E24: Scenario input | F24: editable input | G24: Final QA, handoff, and exception administration.
B25: Workflow overhead | C25: 0.1 | D25: share of direct minutes | E25: Scenario input | F25: editable input | G25: Coordination, rework, interruptions, and other workflow overhead.
B26: PROVIDER PRICING
B27: Text Search Enterprise price | C27: =INDEX('Source register'!$D$6:$D$31,MATCH("api_text_search_price",'Source register'!$B$6:$B$31,0)) -> 35 | D27: $/1,000 events | E27: Published price | F27: api_text_search_price | G27: Google Maps Platform global pay-as-you-go first tier; reviewed 2026-09-03.
B28: Monthly free usage cap | C28: =INDEX('Source register'!$D$6:$D$31,MATCH("api_monthly_free_cap",'Source register'!$B$6:$B$31,0)) -> 1000 | D28: events/month | E28: Published allowance | F28: api_monthly_free_cap | G28: Monthly free usage cap for this Enterprise SKU.
B29: Free allowance allocated to scenario | C29: 0 | D29: share | E29: Scenario input | F29: editable input | G29: Defaults to 0%; allocate only when the allowance is available to this cycle.

Sheet Sensitivity
B2: Scenario range and sensitivity
B3: Shows how area yield, overlap, review time, and exception handling change the effort and cost required to screen the same number of unique sites.
B5: SCENARIO INPUT / OUTPUT | C5: HIGH EFFORT | D5: BASE CASE | E5: LOW EFFORT | F5: PLANNING NOTE
B6: SCENARIO INPUTS
B7: Mapped observations per area | C7: 49 | D7: =Assumptions!C12 -> 93.380952 | E7: 131 | F7: High- and low-effort yields use the observed lower and upper quartiles; Base uses all completed areas.
B8: Cross-search overlap | C8: 0.1 | D8: =Assumptions!C17 -> 0.05354411 | E8: 0.03 | F8: Base is measured cross-area overlap; outer cases test a wider planning range.
B9: Base review seconds/site | C9: 60 | D9: =Assumptions!C20 -> 30 | E9: 20 | F9: First-pass review effort for every candidate.
B10: Review-needed share | C10: 0.2 | D10: =Assumptions!C15 -> 0.24568966 | E10: 0.08 | F10: Share requiring an additional human check.
B11: Review-needed minutes | C11: 4 | D11: =Assumptions!C21 -> 2 | E11: 1 | F11: Extra review time for flagged records.
B12: Search setup minutes | C12: 5 | D12: =Assumptions!C22 -> 3 | E12: 2 | F12: Area setup and run monitoring.
B13: Reconcile/export minutes/search | C13: 3 | D13: =Assumptions!C23 -> 2 | E13: 1 | F13: Cross-run review and export.
B14: Workflow overhead | C14: 0.15 | D14: =Assumptions!C25 -> 0.1 | E14: 0.05 | F14: Coordination, rework, and interruptions.
B15: Review-needed pass rate | C15: 0.3 | D15: =Assumptions!C18 -> 0.5 | E15: 0.7 | F15: Share of flagged records that become outreach-ready.
B16: SCENARIO OUTPUTS
B17: Completed searches | C17: =ROUNDUP(Assumptions!$C$6/(C7*(1-C8)),0) -> 57 | D17: =ROUNDUP(Assumptions!$C$6/(D7*(1-D8)),0) -> 29 | E17: =ROUNDUP(Assumptions!$C$6/(E7*(1-E8)),0) -> 20 | F17: Whole searches required to cover the target.
B18: Paid search calls | C18: =ROUNDUP(C17*Assumptions!$C$13,0) -> 608 | D18: =ROUNDUP(D17*Assumptions!$C$13,0) -> 310 | E18: =ROUNDUP(E17*Assumptions!$C$13,0) -> 214 | F18: Whole API calls required.
B19: Analyst hours | C19: =(((C17*C12)+(Assumptions!$C$6*C9/60)+(ROUND(Assumptions!$C$6*C10,0)*C11)+(C17*C13)+(Assumptions!$C$24*60))*(1+C14))/60 -> 97.29 | D19: =(((D17*D12)+(Assumptions!$C$6*D9/60)+(ROUND(Assumptions!$C$6*D10,0)*D11)+(D17*D13)+(Assumptions!$C$24*60))*(1+D14))/60 -> 50.288333 | E19: =(((E17*E12)+(Assumptions!$C$6*E9/60)+(ROUND(Assumptions!$C$6*E10,0)*E11)+(E17*E13)+(Assumptions!$C$24*60))*(1+E14))/60 -> 21.233333 | F19: Search, review, reconciliation, QA, and overhead.
B20: Gross provider cost | C20: =C18*Assumptions!$C$27/1000 -> 21.28 | D20: =D18*Assumptions!$C$27/1000 -> 10.85 | E20: =E18*Assumptions!$C$27/1000 -> 7.49 | F20: Before monthly free usage is allocated.
B21: Total workflow cost | C21: =C19*Assumptions!$C$10+C20 -> 3329.14 | D21: =D19*Assumptions!$C$10+D20 -> 1720.6533 | E21: =E19*Assumptions!$C$10+E20 -> 729.42333 | F21: Analyst labor plus gross API cost.
B22: Cost per unique site screened | C22: =C21/Assumptions!$C$6 -> 1.331656 | D22: =D21/Assumptions!$C$6 -> 0.68826133 | E22: =E21/Assumptions!$C$6 -> 0.29176933 | F22: Comparable unit cost across scenarios.
B23: Estimated mail-ready sites | C23: =ROUND(Assumptions!$C$6*Assumptions!$C$14,0)+ROUND(ROUND(Assumptions!$C$6*C10,0)*C15,0) -> 1617 | D23: =ROUND(Assumptions!$C$6*Assumptions!$C$14,0)+ROUND(ROUND(Assumptions!$C$6*D10,0)*D15,0) -> 1774 | E23: =ROUND(Assumptions!$C$6*Assumptions!$C$14,0)+ROUND(ROUND(Assumptions!$C$6*E10,0)*E15,0) -> 1607 | F23: Ready records plus flagged records that pass review.
B24: Cost per estimated mail-ready site | C24: =C21/C23 -> 2.0588374 | D24: =D21/D23 -> 0.9699286 | E24: =E21/E23 -> 0.45390375 | F24: Cost after the qualification funnel.
B25: Planning difference vs manual baseline | C25: ='Funnel & cost'!$C$36-C21 -> 3045.86 | D25: ='Funnel & cost'!$C$36-D21 -> 4654.3467 | E25: ='Funnel & cost'!$C$36-E21 -> 5645.5767 | F25: Capacity and budget difference between planning baselines.
B27: TWO-WAY SENSITIVITY — COST PER UNIQUE SITE
B28: REVIEW SEC / OBSERVATIONS PER AREA | C28: 49 | D28: 75 | E28: 93 | F28: 131
B29: 15 | C29: =((((ROUNDUP(Assumptions!$C$6/(C$28*(1-Assumptions!$C$17)),0)*Assumptions!$C$22)+(Assumptions!$C$6*$B29/60)+(Assumptions!$C$6*Assumptions!$C$15*Assumptions!$C$21)+(ROUNDUP(Assumptions!$C$6/(C$28*(1-Assumptions!$C$17)),0)*Assumptions!$C$23)+(Assumptions!$C$24*60))*(1+Assumptions!$C$25))/60*Assumptions!$C$10+ROUNDUP(Assumptions!$C$6/(C$28*(1-Assumptions!$C$17)),0)*Assumptions!$C$13*Assumptions!$C$27/1000)/Assumptions!$C$6 -> 0.56743044 | D29: =((((ROUNDUP(Assumptions!$C$6/(D$28*(1-Assumptions!$C$17)),0)*Assumptions!$C$22)+(Assumptions!$C$6*$B29/60)+(Assumptions!$C$6*Assumptions!$C$15*Assumptions!$C$21)+(ROUNDUP(Assumptions!$C$6/(D$28*(1-Assumptions!$C$17)),0)*Assumptions!$C$23)+(Assumptions!$C$24*60))*(1+Assumptions!$C$25))/60*Assumptions!$C$10+ROUNDUP(Assumptions!$C$6/(D$28*(1-Assumptions!$C$17)),0)*Assumptions!$C$13*Assumptions!$C$27/1000)/Assumptions!$C$6 -> 0.54230244 | E29: =((((ROUNDUP(Assumptions!$C$6/(E$28*(1-Assumptions!$C$17)),0)*Assumptions!$C$22)+(Assumptions!$C$6*$B29/60)+(Assumptions!$C$6*Assumptions!$C$15*Assumptions!$C$21)+(ROUNDUP(Assumptions!$C$6/(E$28*(1-Assumptions!$C$17)),0)*Assumptions!$C$23)+(Assumptions!$C$24*60))*(1+Assumptions!$C$25))/60*Assumptions!$C$10+ROUNDUP(Assumptions!$C$6/(E$28*(1-Assumptions!$C$17)),0)*Assumptions!$C$13*Assumptions!$C$27/1000)/Assumptions!$C$6 -> 0.53253044 | F29: =((((ROUNDUP(Assumptions!$C$6/(F$28*(1-Assumptions!$C$17)),0)*Assumptions!$C$22)+(Assumptions!$C$6*$B29/60)+(Assumptions!$C$6*Assumptions!$C$15*Assumptions!$C$21)+(ROUNDUP(Assumptions!$C$6/(F$28*(1-Assumptions!$C$17)),0)*Assumptions!$C$23)+(Assumptions!$C$24*60))*(1+Assumptions!$C$25))/60*Assumptions!$C$10+ROUNDUP(Assumptions!$C$6/(F$28*(1-Assumptions!$C$17)),0)*Assumptions!$C$13*Assumptions!$C$27/1000)/Assumptions!$C$6 -> 0.52136244
B30: 30 | C30: =((((ROUNDUP(Assumptions!$C$6/(C$28*(1-Assumptions!$C$17)),0)*Assumptions!$C$22)+(Assumptions!$C$6*$B30/60)+(Assumptions!$C$6*Assumptions!$C$15*Assumptions!$C$21)+(ROUNDUP(Assumptions!$C$6/(C$28*(1-Assumptions!$C$17)),0)*Assumptions!$C$23)+(Assumptions!$C$24*60))*(1+Assumptions!$C$25))/60*Assumptions!$C$10+ROUNDUP(Assumptions!$C$6/(C$28*(1-Assumptions!$C$17)),0)*Assumptions!$C$13*Assumptions!$C$27/1000)/Assumptions!$C$6 -> 0.72326377 | D30: =((((ROUNDUP(Assumptions!$C$6/(D$28*(1-Assumptions!$C$17)),0)*Assumptions!$C$22)+(Assumptions!$C$6*$B30/60)+(Assumptions!$C$6*Assumptions!$C$15*Assumptions!$C$21)+(ROUNDUP(Assumptions!$C$6/(D$28*(1-Assumptions!$C$17)),0)*Assumptions!$C$23)+(Assumptions!$C$24*60))*(1+Assumptions!$C$25))/60*Assumptions!$C$10+ROUNDUP(Assumptions!$C$6/(D$28*(1-Assumptions!$C$17)),0)*Assumptions!$C$13*Assumptions!$C$27/1000)/Assumptions!$C$6 -> 0.69813577 | E30: =((((ROUNDUP(Assumptions!$C$6/(E$28*(1-Assumptions!$C$17)),0)*Assumptions!$C$22)+(Assumptions!$C$6*$B30/60)+(Assumptions!$C$6*Assumptions!$C$15*Assumptions!$C$21)+(ROUNDUP(Assumptions!$C$6/(E$28*(1-Assumptions!$C$17)),0)*Assumptions!$C$23)+(Assumptions!$C$24*60))*(1+Assumptions!$C$25))/60*Assumptions!$C$10+ROUNDUP(Assumptions!$C$6/(E$28*(1-Assumptions!$C$17)),0)*Assumptions!$C$13*Assumptions!$C$27/1000)/Assumptions!$C$6 -> 0.68836377 | F30: =((((ROUNDUP(Assumptions!$C$6/(F$28*(1-Assumptions!$C$17)),0)*Assumptions!$C$22)+(Assumptions!$C$6*$B30/60)+(Assumptions!$C$6*Assumptions!$C$15*Assumptions!$C$21)+(ROUNDUP(Assumptions!$C$6/(F$28*(1-Assumptions!$C$17)),0)*Assumptions!$C$23)+(Assumptions!$C$24*60))*(1+Assumptions!$C$25))/60*Assumptions!$C$10+ROUNDUP(Assumptions!$C$6/(F$28*(1-Assumptions!$C$17)),0)*Assumptions!$C$13*Assumptions!$C$27/1000)/Assumptions!$C$6 -> 0.67719577
B31: 45 | C31: =((((ROUNDUP(Assumptions!$C$6/(C$28*(1-Assumptions!$C$17)),0)*Assumptions!$C$22)+(Assumptions!$C$6*$B31/60)+(Assumptions!$C$6*Assumptions!$C$15*Assumptions!$C$21)+(ROUNDUP(Assumptions!$C$6/(C$28*(1-Assumptions!$C$17)),0)*Assumptions!$C$23)+(Assumptions!$C$24*60))*(1+Assumptions!$C$25))/60*Assumptions!$C$10+ROUNDUP(Assumptions!$C$6/(C$28*(1-Assumptions!$C$17)),0)*Assumptions!$C$13*Assumptions!$C$27/1000)/Assumptions!$C$6 -> 0.8790971 | D31: =((((ROUNDUP(Assumptions!$C$6/(D$28*(1-Assumptions!$C$17)),0)*Assumptions!$C$22)+(Assumptions!$C$6*$B31/60)+(Assumptions!$C$6*Assumptions!$C$15*Assumptions!$C$21)+(ROUNDUP(Assumptions!$C$6/(D$28*(1-Assumptions!$C$17)),0)*Assumptions!$C$23)+(Assumptions!$C$24*60))*(1+Assumptions!$C$25))/60*Assumptions!$C$10+ROUNDUP(Assumptions!$C$6/(D$28*(1-Assumptions!$C$17)),0)*Assumptions!$C$13*Assumptions!$C$27/1000)/Assumptions!$C$6 -> 0.8539691 | E31: =((((ROUNDUP(Assumptions!$C$6/(E$28*(1-Assumptions!$C$17)),0)*Assumptions!$C$22)+(Assumptions!$C$6*$B31/60)+(Assumptions!$C$6*Assumptions!$C$15*Assumptions!$C$21)+(ROUNDUP(Assumptions!$C$6/(E$28*(1-Assumptions!$C$17)),0)*Assumptions!$C$23)+(Assumptions!$C$24*60))*(1+Assumptions!$C$25))/60*Assumptions!$C$10+ROUNDUP(Assumptions!$C$6/(E$28*(1-Assumptions!$C$17)),0)*Assumptions!$C$13*Assumptions!$C$27/1000)/Assumptions!$C$6 -> 0.8441971 | F31: =((((ROUNDUP(Assumptions!$C$6/(F$28*(1-Assumptions!$C$17)),0)*Assumptions!$C$22)+(Assumptions!$C$6*$B31/60)+(Assumptions!$C$6*Assumptions!$C$15*Assumptions!$C$21)+(ROUNDUP(Assumptions!$C$6/(F$28*(1-Assumptions!$C$17)),0)*Assumptions!$C$23)+(Assumptions!$C$24*60))*(1+Assumptions!$C$25))/60*Assumptions!$C$10+ROUNDUP(Assumptions!$C$6/(F$28*(1-Assumptions!$C$17)),0)*Assumptions!$C$13*Assumptions!$C$27/1000)/Assumptions!$C$6 -> 0.8330291
B32: 60 | C32: =((((ROUNDUP(Assumptions!$C$6/(C$28*(1-Assumptions!$C$17)),0)*Assumptions!$C$22)+(Assumptions!$C$6*$B32/60)+(Assumptions!$C$6*Assumptions!$C$15*Assumptions!$C$21)+(ROUNDUP(Assumptions!$C$6/(C$28*(1-Assumptions!$C$17)),0)*Assumptions!$C$23)+(Assumptions!$C$24*60))*(1+Assumptions!$C$25))/60*Assumptions!$C$10+ROUNDUP(Assumptions!$C$6/(C$28*(1-Assumptions!$C$17)),0)*Assumptions!$C$13*Assumptions!$C$27/1000)/Assumptions!$C$6 -> 1.0349304 | D32: =((((ROUNDUP(Assumptions!$C$6/(D$28*(1-Assumptions!$C$17)),0)*Assumptions!$C$22)+(Assumptions!$C$6*$B32/60)+(Assumptions!$C$6*Assumptions!$C$15*Assumptions!$C$21)+(ROUNDUP(Assumptions!$C$6/(D$28*(1-Assumptions!$C$17)),0)*Assumptions!$C$23)+(Assumptions!$C$24*60))*(1+Assumptions!$C$25))/60*Assumptions!$C$10+ROUNDUP(Assumptions!$C$6/(D$28*(1-Assumptions!$C$17)),0)*Assumptions!$C$13*Assumptions!$C$27/1000)/Assumptions!$C$6 -> 1.0098024 | E32: =((((ROUNDUP(Assumptions!$C$6/(E$28*(1-Assumptions!$C$17)),0)*Assumptions!$C$22)+(Assumptions!$C$6*$B32/60)+(Assumptions!$C$6*Assumptions!$C$15*Assumptions!$C$21)+(ROUNDUP(Assumptions!$C$6/(E$28*(1-Assumptions!$C$17)),0)*Assumptions!$C$23)+(Assumptions!$C$24*60))*(1+Assumptions!$C$25))/60*Assumptions!$C$10+ROUNDUP(Assumptions!$C$6/(E$28*(1-Assumptions!$C$17)),0)*Assumptions!$C$13*Assumptions!$C$27/1000)/Assumptions!$C$6 -> 1.0000304 | F32: =((((ROUNDUP(Assumptions!$C$6/(F$28*(1-Assumptions!$C$17)),0)*Assumptions!$C$22)+(Assumptions!$C$6*$B32/60)+(Assumptions!$C$6*Assumptions!$C$15*Assumptions!$C$21)+(ROUNDUP(Assumptions!$C$6/(F$28*(1-Assumptions!$C$17)),0)*Assumptions!$C$23)+(Assumptions!$C$24*60))*(1+Assumptions!$C$25))/60*Assumptions!$C$10+ROUNDUP(Assumptions!$C$6/(F$28*(1-Assumptions!$C$17)),0)*Assumptions!$C$13*Assumptions!$C$27/1000)/Assumptions!$C$6 -> 0.98886244
B33: 90 | C33: =((((ROUNDUP(Assumptions!$C$6/(C$28*(1-Assumptions!$C$17)),0)*Assumptions!$C$22)+(Assumptions!$C$6*$B33/60)+(Assumptions!$C$6*Assumptions!$C$15*Assumptions!$C$21)+(ROUNDUP(Assumptions!$C$6/(C$28*(1-Assumptions!$C$17)),0)*Assumptions!$C$23)+(Assumptions!$C$24*60))*(1+Assumptions!$C$25))/60*Assumptions!$C$10+ROUNDUP(Assumptions!$C$6/(C$28*(1-Assumptions!$C$17)),0)*Assumptions!$C$13*Assumptions!$C$27/1000)/Assumptions!$C$6 -> 1.3465971 | D33: =((((ROUNDUP(Assumptions!$C$6/(D$28*(1-Assumptions!$C$17)),0)*Assumptions!$C$22)+(Assumptions!$C$6*$B33/60)+(Assumptions!$C$6*Assumptions!$C$15*Assumptions!$C$21)+(ROUNDUP(Assumptions!$C$6/(D$28*(1-Assumptions!$C$17)),0)*Assumptions!$C$23)+(Assumptions!$C$24*60))*(1+Assumptions!$C$25))/60*Assumptions!$C$10+ROUNDUP(Assumptions!$C$6/(D$28*(1-Assumptions!$C$17)),0)*Assumptions!$C$13*Assumptions!$C$27/1000)/Assumptions!$C$6 -> 1.3214691 | E33: =((((ROUNDUP(Assumptions!$C$6/(E$28*(1-Assumptions!$C$17)),0)*Assumptions!$C$22)+(Assumptions!$C$6*$B33/60)+(Assumptions!$C$6*Assumptions!$C$15*Assumptions!$C$21)+(ROUNDUP(Assumptions!$C$6/(E$28*(1-Assumptions!$C$17)),0)*Assumptions!$C$23)+(Assumptions!$C$24*60))*(1+Assumptions!$C$25))/60*Assumptions!$C$10+ROUNDUP(Assumptions!$C$6/(E$28*(1-Assumptions!$C$17)),0)*Assumptions!$C$13*Assumptions!$C$27/1000)/Assumptions!$C$6 -> 1.3116971 | F33: =((((ROUNDUP(Assumptions!$C$6/(F$28*(1-Assumptions!$C$17)),0)*Assumptions!$C$22)+(Assumptions!$C$6*$B33/60)+(Assumptions!$C$6*Assumptions!$C$15*Assumptions!$C$21)+(ROUNDUP(Assumptions!$C$6/(F$28*(1-Assumptions!$C$17)),0)*Assumptions!$C$23)+(Assumptions!$C$24*60))*(1+Assumptions!$C$25))/60*Assumptions!$C$10+ROUNDUP(Assumptions!$C$6/(F$28*(1-Assumptions!$C$17)),0)*Assumptions!$C$13*Assumptions!$C$27/1000)/Assumptions!$C$6 -> 1.3005291
B35: Planning insight | C35: Review effort remains the largest modeled cost driver. Search yield and overlap now use the completed market run; update yellow inputs as operating conditions change.

Sheet Outcome plan
B2: Campaign outcome tracker
B3: Complete this sheet after a campaign closes to connect list production, outreach, contracts, and total acquisition cost.
B5: CAMPAIGN INPUT | C5: VALUE | D5: UNIT / STATUS | E5: DEFINITION | F5: REQUIRED? | G5: NOTES
B6: Campaign start date | D6: Enter date | E6: First outreach date | F6: Required
B7: Measurement close date | D7: Enter date | E7: Date used to close the reporting window | F7: Required
B8: Campaign / mailing-batch ID | D8: Enter ID | E8: Code carried through list, outreach, response, and agreement records | F8: Required
B9: Unique sites screened | D9: Enter count | E9: Reconciled distinct physical sites | F9: Required
B10: Ready after review | D10: Enter count | E10: Sites approved for outreach | F10: Required
B11: Actual analyst research hours | D11: Enter hours | E11: Time record for search, review, reconcile, export, QA | F11: Required
B12: Actual loaded analyst cost | D12: Enter $/hour | E12: Finance-approved rate | F12: Required
B13: Actual API invoice allocation | D13: Enter $ | E13: Campaign share of provider charges after approved account-level credits | F13: Required
B14: Pieces mailed | D14: Enter count | E14: Dated vendor/campaign count | F14: Required
B15: Print/postage invoice | D15: Enter $ | E15: Actual invoice, not unit estimate | F15: Required
B16: Mailing vendor/setup cost | D16: Enter $ | E16: Data prep, printing setup, list/vendor fees | F16: Required
B17: BD follow-up hours | D17: Enter hours | E17: Time responding, qualifying, negotiating | F17: Required
... B23: Productive sites | D23: Enter count | E23: Signed sites reaching agreed productive-state definition | F23: Required
B25: CALCULATED CAMPAIGN KPIs
B26: OUTCOME KPI | C26: RESULT | D26: UNIT | E26: WHAT IT SHOWS | F26: DATA NEEDED | G26: STATUS
B27: List-production cost | C27: =IF(OR(C11="",C12="",C13=""),"",C11*C12+C13) | D27: $ | E27: Research labor plus allocated provider cost. | F27: All three actual inputs required. | G27: =IF(C27="","NEEDED","CALCULATED") -> NEEDED
B28: BD labor cost | C28: =IF(OR(C17="",C18=""),"",C17*C18) | D28: $ | E28: Follow-up labor after outreach. | F28: Actual time and rate required. | G28: =IF(C28="","NEEDED","CALCULATED") -> NEEDED
B29: TOTAL campaign acquisition cost | C29: =IF(OR(C27="",C15="",C16="",C28="",C19=""),"",C27+C15+C16+C28+C19) | D29: $ | E29: List production, mail/vendor, BD follow-up, and onboarding/other campaign costs. | F29: Use for total campaign CAC. | G29: =IF(C29="","NEEDED","CALCULATED") -> NEEDED
B30: Response rate | C30: =IFERROR(C20/C14,"") | D30: % | E30: Responses ÷ pieces mailed. | F30: Dated numerator and denominator. | G30: =IF(C30="","NEEDED","CALCULATED") -> NEEDED
B31: Ready-to-response conversion | C31: =IFERROR(C20/C10,"") | D31: % | E31: Responses ÷ outreach-ready sites. | F31: Consistent campaign definition. | G31: =IF(C31="","NEEDED","CALCULATED") -> NEEDED
B32: Response-to-signed conversion | C32: =IFERROR(C22/C20,"") | D32: % | E32: Signed contracts ÷ responses. | F32: Attribution rule required. | G32: =IF(C32="","NEEDED","CALCULATED") -> NEEDED
B33: Mailing-only cost per signed contract | C33: =IFERROR((C15+C16)/C22,"") | D33: $ | E33: Print/postage plus mailing vendor cost per signed contract. | F33: Label as mailing-only. | G33: =IF(C33="","NEEDED","CALCULATED") -> NEEDED
B34: TOTAL CAC per signed contract | C34: =IFERROR(C29/C22,"") | D34: $ | E34: Total cohort acquisition cost ÷ signed contracts. | F34: Primary acquisition-cost KPI. | G34: =IF(C34="","NEEDED","CALCULATED") -> NEEDED
B35: Cost per productive site | C35: =IFERROR(C29/C23,"") | D35: $ | E35: Total cohort acquisition cost ÷ productive sites. | F35: Define productive state and window. | G35: =IF(C35="","NEEDED","CALCULATED") -> NEEDED
B36: Signed-to-productive conversion | C36: =IFERROR(C23/C22,"") | D36: % | E36: Productive sites ÷ signed contracts. | F36: Close reporting after sufficient maturity. | G36: =IF(C36="","NEEDED","CALCULATED") -> NEEDED

Sheet Source register
B2: Inputs and sources
B3: Reference values used by the planning model, with stable lookup keys, source dates, and notes on how each value is used.
B5: SOURCE KEY | C5: METRIC | D5: VALUE | E5: UNIT | F5: INPUT TYPE | G5: AS OF | H5: SOURCE | I5: USE IN MODEL
B6: manual_target_per_day | C6: Manual activity target | D6: 40 | E6: sites/day | F6: Operating baseline | G6: 2026-08-31 | H6: Prior operating workflow | I6: Manual list-building target used for the planning baseline.
B7: manual_hours_per_day | C7: Time assigned to prospecting | D7: 3 | E7: hours/day | F7: Operating baseline | G7: 2026-08-31 | H7: Prior operating workflow | I7: Time assigned to manual prospecting in the prior workflow.
B8: val_results_per_search | C8: Mapped observations per completed area | D8: 93.380952 | E8: observations/area | F8: Completed market run | G8: 2026-09-04 | H8: run-20260904-024050-et | I8: 1,961 observations across 21 completed areas.
B9: val_calls_per_search | C9: API calls per completed area | D9: 10.666667 | E9: calls/area | F9: Completed market run | G9: 2026-09-04 | H9: run-20260904-024050-et | I9: 224 calls across 21 completed areas.
B10: val_ready_count | C10: Ready for outreach | D10: 1089 | E10: primary Place-ID records | F10: Current qualification output | G10: 2026-09-04 | H10: run-20260904-024050-et | I10: Meets the current outreach-ready rule.
B11: val_verify_count | C11: Review needed | D11: 456 | E11: primary Place-ID records | F11: Current qualification output | G11: 2026-09-04 | H11: run-20260904-024050-et | I11: Requires a human check before outreach; verified records can move to Ready.
B12: val_not_viable_count | C12: Not currently viable | D12: 311 | E12: primary Place-ID records | F12: Current qualification output | G12: 2026-09-04 | H12: run-20260904-024050-et | I12: Does not currently meet the outreach rule.
B13: val_bucket_total | C13: Qualification control total | D13: 1856 | E13: primary Place-ID records | F13: Control total | G13: 2026-09-04 | H13: run-20260904-024050-et | I13: Ready + Review needed + Not currently viable; Place-ID deduplication does not prove distinct physical sites.
B14: val_overlap_rate | C14: Cross-area repeat rate | D14: 0.05354411 | E14: share | F14: Completed market run | G14: 2026-09-04 | H14: run-20260904-024050-et | I14: 105 repeat observations removed from 1,961 observations.
B15: api_text_search_price | C15: Places API Text Search Enterprise | D15: 35 | E15: $/1,000 events | F15: Published price | G15: 2026-09-03 | H15: Google Maps Platform pricing | I15: Global pay-as-you-go first tier; recheck when budgeting.
B16: api_monthly_free_cap | C16: Places API Text Search Enterprise free usage | D16: 1000 | E16: events/month | F16: Published allowance | G16: 2026-09-03 | H16: Google Maps Platform pricing | I16: Monthly free usage cap for this Enterprise SKU; allocation is handled separately.
B17: cloud_request_count | C17: Google Cloud request count | D17: 224 | E17: requests | F17: Console reconciliation | G17: 2026-09-04 | H17: Google Cloud console | I17: Matches the isolated application ledger for the completed run.
... B19: market_run_call_cap | C19: Approved market-run call cap | D19: 225 | E19: calls | F19: Pre-registered run control | G19: 2026-09-04 | H19: run-20260904-024050-et | I19: Hard ceiling for the bounded market run.

Sheet Validation summary
B2: Technical results
B3: Formula summaries and charts connect the focused controls with the completed 21-area market run, cache reuse, qualification, and spatial filtering.
B5: Search yield and cache reuse
B6: TEST GROUP | C6: VARIANT | D6: ROWS | E6: TOTAL RESULTS | F6: TOTAL CALLS | G6: AVG RESULTS / CALL
B7: Density | C7: Cold | D7: =COUNTIFS('Raw validation'!$B:$B,B7,'Raw validation'!$E:$E,C7) -> 3 | E7: =SUMIFS('Raw validation'!$H:$H,'Raw validation'!$B:$B,B7,'Raw validation'!$E:$E,C7) -> 218 | F7: =SUMIFS('Raw validation'!$I:$I,'Raw validation'!$B:$B,B7,'Raw validation'!$E:$E,C7) -> 23 | G7: =IFERROR(E7/F7,"") -> 9.4782609
B8: Density | C8: Warm | D8: =COUNTIFS('Raw validation'!$B:$B,B8,'Raw validation'!$E:$E,C8) -> 3 | E8: =SUMIFS('Raw validation'!$H:$H,'Raw validation'!$B:$B,B8,'Raw validation'!$E:$E,C8) -> 218 | F8: =SUMIFS('Raw validation'!$I:$I,'Raw validation'!$B:$B,B8,'Raw validation'!$E:$E,C8) -> 0 | G8: =IFERROR(E8/F8,"")
B9: Saturation | C9: Cold | D9: =COUNTIFS('Raw validation'!$B:$B,B9,'Raw validation'!$E:$E,C9) -> 1 | E9: =SUMIFS('Raw validation'!$H:$H,'Raw validation'!$B:$B,B9,'Raw validation'!$E:$E,C9) -> 85 | F9: =SUMIFS('Raw validation'!$I:$I,'Raw validation'!$B:$B,B9,'Raw validation'!$E:$E,C9) -> 10 | G9: =IFERROR(E9/F9,"") -> 8.5
B10: Saturation | C10: Warm | D10: =COUNTIFS('Raw validation'!$B:$B,B10,'Raw validation'!$E:$E,C10) -> 1 | E10: =SUMIFS('Raw validation'!$H:$H,'Raw validation'!$B:$B,B10,'Raw validation'!$E:$E,C10) -> 85 | F10: =SUMIFS('Raw validation'!$I:$I,'Raw validation'!$B:$B,B10,'Raw validation'!$E:$E,C10) -> 0 | G10: =IFERROR(E10/F10,"")
B12: Cold search by market
B13: CASE ID | C13: MARKET | D13: RESULTS | E13: CALLS | F13: RESULTS / CALL | G13: REPEAT RESULT DIGEST
B14: sparse_barstow | C14: Barstow | D14: =SUMIFS('Raw validation'!$H:$H,'Raw validation'!$C:$C,B14,'Raw validation'!$E:$E,"Cold") -> 63 | E14: =SUMIFS('Raw validation'!$I:$I,'Raw validation'!$C:$C,B14,'Raw validation'!$E:$E,"Cold") -> 7 | F14: =IFERROR(D14/E14,"") -> 9 | G14: =IF(COUNTIFS('Raw validation'!$C:$C,B14,'Raw validation'!$E:$E,"Warm",'Raw validation'!$H:$H,D14)=1,"MATCH","CHECK") -> MATCH
B15: medium_riverside | C15: Riverside | D15: =SUMIFS('Raw validation'!$H:$H,'Raw validation'!$C:$C,B15,'Raw validation'!$E:$E,"Cold") -> 49 | E15: =SUMIFS('Raw validation'!$I:$I,'Raw validation'!$C:$C,B15,'Raw validation'!$E:$E,"Cold") -> 7 | F15: =IFERROR(D15/E15,"") -> 7 | G15: =IF(COUNTIFS('Raw validation'!$C:$C,B15,'Raw validation'!$E:$E,"Warm",'Raw validation'!$H:$H,D15)=1,"MATCH","CHECK") -> MATCH
B16: dense_downtown_la | C16: Downtown Los Angeles | D16: =SUMIFS('Raw validation'!$H:$H,'Raw validation'!$C:$C,B16,'Raw validation'!$E:$E,"Cold") -> 106 | E16: =SUMIFS('Raw validation'!$I:$I,'Raw validation'!$C:$C,B16,'Raw validation'!$E:$E,"Cold") -> 9 | F16: =IFERROR(D16/E16,"") -> 11.777778 | G16: =IF(COUNTIFS('Raw validation'!$C:$C,B16,'Raw validation'!$E:$E,"Warm",'Raw validation'!$H:$H,D16)=1,"MATCH","CHECK") -> MATCH
B17: saturation_downtown_la_convenience | C17: Downtown LA saturation | D17: =SUMIFS('Raw validation'!$H:$H,'Raw validation'!$C:$C,B17,'Raw validation'!$E:$E,"Cold") -> 85 | E17: =SUMIFS('Raw validation'!$I:$I,'Raw validation'!$C:$C,B17,'Raw validation'!$E:$E,"Cold") -> 10 | F17: =IFERROR(D17/E17,"") -> 8.5 | G17: =IF(COUNTIFS('Raw validation'!$C:$C,B17,'Raw validation'!$E:$E,"Warm",'Raw validation'!$H:$H,D17)=1,"MATCH","CHECK") -> MATCH
B19: Current market-run qualification mix
B20: BUCKET | C20: COUNT | D20: SHARE | E20: SOURCE KEY | F20: WHAT IT MEANS
B21: Ready | C21: =INDEX('Source register'!$D$6:$D$31,MATCH("val_ready_count",'Source register'!$B$6:$B$31,0)) -> 1089 | D21: =C21/$C$24 -> 0.58674569 | E21: val_ready_count | F21: Meets the current outreach-ready rule.
B22: Review needed | C22: =INDEX('Source register'!$D$6:$D$31,MATCH("val_verify_count",'Source register'!$B$6:$B$31,0)) -> 456 | D22: =C22/$C$24 -> 0.24568966 | E22: val_verify_count | F22: Requires a human check; verified records can move to Ready.
B23: Not currently viable | C23: =INDEX('Source register'!$D$6:$D$31,MATCH("val_not_viable_count",'Source register'!$B$6:$B$31,0)) -> 311 | D23: =C23/$C$24 -> 0.16756466 | E23: val_not_viable_count | F23: Does not currently meet the outreach rule.
B24: CONTROL TOTAL | C24: =SUM(C21:C23) -> 1856 | D24: =SUM(D21:D23) -> 1 | E24: val_bucket_total | F24: =IF(C24=INDEX('Source register'!$D$6:$D$31,MATCH(E24,'Source register'!$B$6:$B$31,0)),"PASS","FAIL") -> PASS
B26: Spatial filtering check
B27: MODE | C27: TESTS | D27: RESULTS | E27: OUTSIDE RECT | F27: OUTSIDE RECT SHARE
B28: Bias | C28: =COUNTIFS('Raw validation'!$B:$B,"Spatial A/B",'Raw validation'!$E:$E,B28) -> 3 | D28: =SUMIFS('Raw validation'!$H:$H,'Raw validation'!$B:$B,"Spatial A/B",'Raw validation'!$E:$E,B28) -> 60 | E28: =SUMIFS('Raw validation'!$O:$O,'Raw validation'!$B:$B,"Spatial A/B",'Raw validation'!$E:$E,B28) -> 31 | F28: =IFERROR(E28/D28,"") -> 0.51666667
B29: Restriction | C29: =COUNTIFS('Raw validation'!$B:$B,"Spatial A/B",'Raw validation'!$E:$E,B29) -> 3 | D29: =SUMIFS('Raw validation'!$H:$H,'Raw validation'!$B:$B,"Spatial A/B",'Raw validation'!$E:$E,B29) -> 26 | E29: =SUMIFS('Raw validation'!$O:$O,'Raw validation'!$B:$B,"Spatial A/B",'Raw validation'!$E:$E,B29) -> 0 | F29: =IFERROR(E29/D29,"") -> 0
B34: Completed market run · 2026-09-04
B35: METRIC | C35: RESULT | D35: UNIT | E35: EVIDENCE | F35: OPERATIONAL READING
B36: Completed areas | C36: 21 | D36: of 25 | E36: Run ledger | F36: Four remaining areas were not started after the call guard reserved the final call.
B37: Unique returned primary Place IDs | C37: 1856 | D37: records | E37: Place-ID deduplication | F37: Reduced 1,961 observations to a reusable market list; this does not by itself prove distinct physical sites.
B38: API calls | C38: 224 | D38: calls | E38: Ledger + operator-recorded Cloud count | F38: The application ledger matched the Google Cloud request count; eight aggregate error events remained unclassified.
B39: Gross searched area | C39: 412.3 | D39: km² | E39: Completed circles | F39: Gross circle area; neighboring-circle overlap is retained in this coverage measure.
B40: Unique primary Place IDs per call | C40: 8.29 | D40: records/call | E40: Derived | F40: Observed record throughput across the completed run.
B41: Cell runtime | C41: 4.30 / 8.16 | D41: median / p95 sec | E41: Run timing | F41: Interactive search latency across completed areas.
B42: Warm repeat controls | C42: 4 / 4 | D42: matched | E42: Cache controls | F42: Identical candidate digests returned with zero new provider calls.
B43: Manual category review | C43: 48 / 50 | D43: plausible | E43: Deterministic sample | F43: Two category mismatches were retained as data-quality findings.

Sheet Raw validation
B2: Technical search validation
B3: Recorded search variants used to check market yield, cache behavior, and spatial filtering in the current implementation.
B5: TEST GROUP | C5: CASE ID | D5: MARKET / LABEL | E5: VARIANT | F5: RADIUS M | G5: SEGMENTS / QUERY | H5: RESULTS | I5: API CALLS | J5: CACHE HITS | K5: TILES | L5: TRUNCATED | M5: RESULTS / CALL | N5: OUTSIDE CIRCLE | O5: OUTSIDE RECT | P5: FARTHEST M | Q5: RESULT DIGEST | R5: RUN ID / AS OF | S5: EVIDENCE STATUS
B6: Density | C6: sparse_barstow | D6: Barstow, CA | E6: Cold | F6: 2500 | G6: smoke, liquor, gas, laundromat, convenience | H6: 63 | I6: 7 | J6: 0 | K6: 5 | L6: None | M6: =IFERROR(H6/I6,"") -> 9 | Q6: 682ec3f93e92de70306445e4dc08c540f1b9e26fe26df9fffcaf72fb0a067eb7 | R6: run-20260831-212343-et | S6: Current technical check
B7: Density | C7: sparse_barstow | D7: Barstow, CA | E7: Warm | F7: 2500 | G7: smoke, liquor, gas, laundromat, convenience | H7: 63 | I7: 0 | J7: 5 | K7: 5 | L7: None | M7: =IFERROR(H7/I7,"") | Q7: 682ec3f93e92de70306445e4dc08c540f1b9e26fe26df9fffcaf72fb0a067eb7 | R7: run-20260831-212343-et | S7: Current technical check
B8: Density | C8: medium_riverside | D8: Riverside, CA | E8: Cold | F8: 2500 | G8: smoke, liquor, gas, laundromat, convenience | H8: 49 | I8: 7 | J8: 0 | K8: 5 | L8: None | M8: =IFERROR(H8/I8,"") -> 7 | Q8: da09696c191bd4e71cfdc3274c5d1456991855d6100f2c19a907ab921c852398 | R8: run-20260831-212343-et | S8: Current technical check
B9: Density | C9: medium_riverside | D9: Riverside, CA | E9: Warm | F9: 2500 | G9: smoke, liquor, gas, laundromat, convenience | H9: 49 | I9: 0 | J9: 5 | K9: 5 | L9: None | M9: =IFERROR(H9/I9,"") | Q9: da09696c191bd4e71cfdc3274c5d1456991855d6100f2c19a907ab921c852398 | R9: run-20260831-212343-et | S9: Current technical check
B10: Density | C10: dense_downtown_la | D10: Downtown Los Angeles, CA | E10: Cold | F10: 2500 | G10: smoke, liquor, gas, laundromat, convenience | H10: 106 | I10: 9 | J10: 0 | K10: 5 | L10: None | M10: =IFERROR(H10/I10,"") -> 11.777778 | Q10: f9c7bfec15cc98a8a4ed7daacf92d5cc49ae95508bd6f377ee8409ed3c95f901 | R10: run-20260831-212343-et | S10: Current technical check
B11: Density | C11: dense_downtown_la | D11: Downtown Los Angeles, CA | E11: Warm | F11: 2500 | G11: smoke, liquor, gas, laundromat, convenience | H11: 106 | I11: 0 | J11: 5 | K11: 5 | L11: None | M11: =IFERROR(H11/I11,"") | Q11: f9c7bfec15cc98a8a4ed7daacf92d5cc49ae95508bd6f377ee8409ed3c95f901 | R11: run-20260831-212343-et | S11: Current technical check
B12: Saturation | C12: saturation_downtown_la_convenience | D12: Downtown Los Angeles 5 km convenience saturation probe | E12: Cold | F12: 5000 | G12: convenience | H12: 85 | I12: 10 | J12: 0 | K12: 5 | L12: None | M12: =IFERROR(H12/I12,"") -> 8.5 | Q12: 849e05c31ce30a6847a7f67a1237d1a4ecb0ed01d4ad0f1e753502962d0397cf | R12: run-20260831-212343-et | S12: Current technical check
B13: Saturation | C13: saturation_downtown_la_convenience | D13: Downtown Los Angeles 5 km convenience saturation probe | E13: Warm | F13: 5000 | G13: convenience | H13: 85 | I13: 0 | J13: 5 | K13: 5 | L13: None | M13: =IFERROR(H13/I13,"") | Q13: 849e05c31ce30a6847a7f67a1237d1a4ecb0ed01d4ad0f1e753502962d0397cf | R13: run-20260831-212343-et | S13: Current technical check
B14: Spatial A/B | C14: la_convenience | D14: Downtown Los Angeles / convenience | E14: Bias | F14: 1000 | G14: convenience store mini mart | H14: 20 | I14: 1 | M14: =IFERROR(H14/I14,"") -> 20 | N14: 10 | O14: 7 | P14: 6023 | R14: run-20260831-212343-et | S14: Current technical check
B15: Spatial A/B | C15: la_convenience | D15: Downtown Los Angeles / convenience | E15: Restriction | F15: 1000 | G15: convenience store mini mart | H15: 12 | I15: 1 | M15: =IFERROR(H15/I15,"") -> 12 | N15: 2 | O15: 0 | P15: 1360.5 | R15: run-20260831-212343-et | S15: Current technical check
B16: Spatial A/B | C16: riverside_gas | D16: Riverside / gas | E16: Bias | F16: 1000 | G16: gas station | H16: 20 | I16: 1 | M16: =IFERROR(H16/I16,"") -> 20 | N16: 15 | O16: 15 | P16: 3392.7 | R16: run-20260831-212343-et | S16: Current technical check
B17: Spatial A/B | C17: riverside_gas | D17: Riverside / gas | E17: Restriction | F17: 1000 | G17: gas station | H17: 4 | I17: 1 | M17: =IFERROR(H17/I17,"") -> 4 | N17: 0 | O17: 0 | P17: 768.2 | R17: run-20260831-212343-et | S17: Current technical check
B18: Spatial A/B | C18: koreatown_liquor | D18: Koreatown / liquor | E18: Bias | F18: 1000 | G18: liquor store wine spirits | H18: 20 | I18: 1 | M18: =IFERROR(H18/I18,"") -> 20 | N18: 12 | O18: 9 | P18: 4791 | R18: run-20260831-212343-et | S18: Current technical check
B19: Spatial A/B | C19: koreatown_liquor | D19: Koreatown / liquor | E19: Restriction | F19: 1000 | G19: liquor store wine spirits | H19: 10 | I19: 1 | M19: =IFERROR(H19/I19,"") -> 10 | N19: 3 | O19: 0 | P19: 1173.1 | R19: run-20260831-212343-et | S19: Current technical check
B20: Market grid | C20: r1c1 | D20: Los Angeles grid | E20: Cold | F20: 2500 | G20: smoke, liquor, gas, laundromat, convenience | H20: 99 | I20: 13 | J20: 0 | K20: 9 | L20: None | M20: =IFERROR(H20/I20,"") -> 7.6153846 | Q20: bd5fb2e818b8a3d450b47f9a30e2d9fef8eb0e0709dd372ee5cdb04b0b2e67ec | R20: run-20260904-024050-et | S20: Completed market run
B21: Market grid | C21: r1c2 | D21: Los Angeles grid | E21: Cold | F21: 2500 | G21: smoke, liquor, gas, laundromat, convenience | H21: 144 | I21: 11 | J21: 0 | K21: 5 | L21: None | M21: =IFERROR(H21/I21,"") -> 13.090909 | Q21: ba675a958493a5466c3c99a6f92a705abfc32d0c3703808a360d2f52d045fb7d | R21: run-20260904-024050-et | S21: Completed market run
B22: Market grid | C22: r1c3 | D22: Los Angeles grid | E22: Cold | F22: 2500 | G22: smoke, liquor, gas, laundromat, convenience | H22: 133 | I22: 16 | J22: 0 | K22: 9 | L22: None | M22: =IFERROR(H22/I22,"") -> 8.3125 | Q22: e3a5a405552c16de37cc3a8a73b5ba72561ecd2c56095711a7f3c94005f13a73 | R22: run-20260904-024050-et | S22: Completed market run
B23: Market grid | C23: r1c4 | D23: Los Angeles grid | E23: Cold | F23: 2500 | G23: smoke, liquor, gas, laundromat, convenience | H23: 108 | I23: 10 | J23: 0 | K23: 5 | L23: None | M23: =IFERROR(H23/I23,"") -> 10.8 | Q23: 78e2350dd9560fa87c5b650d739217f37c4a8f7151b2935006a0171ef7ac33f7 | R23: run-20260904-024050-et | S23: Completed market run
B24: Market grid | C24: r1c5 | D24: Los Angeles grid | E24: Cold | F24: 2500 | G24: smoke, liquor, gas, laundromat, convenience | H24: 55 | I24: 6 | J24: 0 | K24: 5 | L24: None | M24: =IFERROR(H24/I24,"") -> 9.1666667 | Q24: 150def406cb492cb5bae2ab675aeebea8e6bd2b8255777e60a42e5209463a23d | R24: run-20260904-024050-et | S24: Completed market run
B25: Market grid | C25: r2c1 | D25: Los Angeles grid | E25: Cold | F25: 2500 | G25: smoke, liquor, gas, laundromat, convenience | H25: 49 | I25: 6 | J25: 0 | K25: 5 | L25: None | M25: =IFERROR(H25/I25,"") -> 8.1666667 | Q25: 6d47ed875d14583b82c24182dfea08c9bfa98b9a474affae0e9e234a7b5781f9 | R25: run-20260904-024050-et | S25: Completed market run
B26: Market grid | C26: r2c2 | D26: Los Angeles grid | E26: Cold | F26: 2500 | G26: smoke, liquor, gas, laundromat, convenience | H26: 128 | I26: 11 | J26: 0 | K26: 5 | L26: None | M26: =IFERROR(H26/I26,"") -> 11.636364 | Q26: 4cb668e4983321c2e1786fe4a397d0bc964b59eb6bc1107f7f3f9cedfc2ce4a1 | R26: run-20260904-024050-et | S26: Completed market run
B27: Market grid | C27: r2c3 | D27: Los Angeles grid | E27: Cold | F27: 2500 | G27: smoke, liquor, gas, laundromat, convenience | H27: 102 | I27: 14 | J27: 0 | K27: 9 | L27: None | M27: =IFERROR(H27/I27,"") -> 7.2857143 | Q27: 7cdc7ed7618981e8114801abf1a2e59274c96fbc431e842d73a40b7f65b143b1 | R27: run-20260904-024050-et | S27: Completed market run
B28: Market grid | C28: r2c4 | D28: Los Angeles grid | E28: Cold | F28: 2500 | G28: smoke, liquor, gas, laundromat, convenience | H28: 49 | I28: 7 | J28: 0 | K28: 5 | L28: None | M28: =IFERROR(H28/I28,"") -> 7 | Q28: 6f9c73f41ff798bd5163618a2a2ad0ee95992deb3d18db956d08afa459a74310 | R28: run-20260904-024050-et | S28: Completed market run
B29: Market grid | C29: r2c5 | D29: Los Angeles grid | E29: Cold | F29: 2500 | G29: smoke, liquor, gas, laundromat, convenience | H29: 73 | I29: 8 | J29: 0 | K29: 5 | L29: None | M29: =IFERROR(H29/I29,"") -> 9.125 | Q29: c60c6b2f66c01dbc824fcdca06a1d8ae8532071dba3a0bc1e3a1358f5b143c1c | R29: run-20260904-024050-et | S29: Completed market run
B30: Market grid | C30: r3c1 | D30: Los Angeles grid | E30: Cold | F30: 2500 | G30: smoke, liquor, gas, laundromat, convenience | H30: 102 | I30: 9 | J30: 0 | K30: 5 | L30: None | M30: =IFERROR(H30/I30,"") -> 11.333333 | Q30: 02fee1f06e504ad12215e18bc64c8bc2c4334240cdab08c443db92b7e7ccd8dd | R30: run-20260904-024050-et | S30: Completed market run
B31: Market grid | C31: r3c2 | D31: Los Angeles grid | E31: Cold | F31: 2500 | G31: smoke, liquor, gas, laundromat, convenience | H31: 224 | I31: 25 | J31: 0 | K31: 13 | L31: None | M31: =IFERROR(H31/I31,"") -> 8.96 | Q31: 70ecba610aab5183ddb04763656f1c7c65d1a02d0f8b2745c49750d8a59413d7 | R31: run-20260904-024050-et | S31: Completed market run
... B44: Market grid | C44: r5c1 | D44: Los Angeles grid | E44: Warm | F44: 2500 | G44: smoke, liquor, gas, laundromat, convenience | H44: 16 | I44: 0 | J44: 5 | K44: 5 | L44: None | M44: =IFERROR(H44/I44,"") | Q44: d82e5c31f23899dc898e07b77f860c38b8aaa7c33c0f08a8595257fda23379d1 | R44: run-20260904-024050-et | S44: Cache replay control

Sheet Pivot table
B2: Validation PivotTable
B3: Summarizes the Technical search validation table by test group and run type. Refresh after changing the source rows.
B5: Rows: test group · Columns: run type · Values: mapped results and API calls
C7: VARIANT | D7: Values
C8: Bias | E8: Cold | G8: Restriction | I8: Warm | K8: Total Sum of Results | L8: Total Sum of API Calls
B9: TEST GROUP | C9: Sum of Results | D9: Sum of API Calls | E9: Sum of Results | F9: Sum of API Calls | G9: Sum of Results | H9: Sum of API Calls | I9: Sum of Results | J9: Sum of API Calls
B10: Density | E10: 218 | F10: 23 | I10: 218 | J10: 0 | K10: 436 | L10: 23
B11: Market grid | E11: 1961 | F11: 224 | I11: 283 | J11: 0 | K11: 2244 | L11: 224
B12: Saturation | E12: 85 | F12: 10 | I12: 85 | J12: 0 | K12: 170 | L12: 10
B13: Spatial A/B | C13: 60 | D13: 3 | G13: 26 | H13: 3 | K13: 86 | L13: 6
B14: Grand Total | C14: 60 | D14: 3 | E14: 2264 | F14: 257 | G14: 26 | H14: 3 | I14: 586 | J14: 0 | K14: 2936 | L14: 263

Sheet Reconciliation & QA
B2: Model checks
B3: Formula checks confirm that funnel totals, usage, pricing, and costs remain internally consistent.
B5: CHECK ID | C5: CHECK | D5: ACTUAL | E5: EXPECTED | F5: STATUS | G5: IF IT FAILS
B6: QA-01 | C6: Source bucket counts sum to source total | D6: =SUM('Validation summary'!C21:C23) -> 1856 | E6: =INDEX('Source register'!$D$6:$D$31,MATCH("val_bucket_total",'Source register'!$B$6:$B$31,0)) -> 1856 | F6: =IF(D6=E6,"PASS","FAIL") -> PASS | G6: Review source register/bucket import.
B7: QA-02 | C7: Classification shares sum to 100% | D7: =SUM(Assumptions!C14:C16) -> 1 | E7: 1 | F7: =IF(ABS(D7-E7)<0.000001,"PASS","FAIL") -> PASS | G7: Correct share formulas.
B8: QA-03 | C8: Qualification stages sum to screened target | D8: ='Funnel & cost'!D19 -> 2500 | E8: ='Funnel & cost'!D7 -> 2500 | F8: =IF(ABS(D8-E8)<0.001,"PASS","FAIL") -> PASS | G8: Review Ready / Review needed / Not currently viable formulas.
B9: QA-04 | C9: Completed searches are a whole number | D9: ='Funnel & cost'!D9 -> 29 | E9: =ROUND(D9,0) -> 29 | F9: =IF(D9=E9,"PASS","FAIL") -> PASS | G9: Use ROUNDUP.
B10: QA-05 | C10: Paid calls are a whole number | D10: ='Funnel & cost'!D31 -> 310 | E10: =ROUND(D10,0) -> 310 | F10: =IF(D10=E10,"PASS","FAIL") -> PASS | G10: Searches × calls/search must be integer.
B11: QA-06 | C11: Estimated returned primary Place IDs meet planning target | D11: ='Funnel & cost'!D12 -> 2563.0476 | E11: ='Funnel & cost'!D7 -> 2500 | F11: =IF(D11>=E11,"PASS","FAIL") -> PASS | G11: Increase searches or revise overlap/yield.
B12: QA-07 | C12: Net provider cost equals gross less credit | D12: ='Funnel & cost'!D35 -> 10.85 | E12: =MAX(0,'Funnel & cost'!D32-'Funnel & cost'!D34) -> 10.85 | F12: =IF(ABS(D12-E12)<0.001,"PASS","FAIL") -> PASS | G12: Review credit allocation.
B13: QA-08 | C13: Tool total equals labor plus net provider | D13: ='Funnel & cost'!D36 -> 1720.6533 | E13: ='Funnel & cost'!D29+'Funnel & cost'!D35 -> 1720.6533 | F13: =IF(ABS(D13-E13)<0.001,"PASS","FAIL") -> PASS | G13: Review cost component formulas.
B14: QA-09 | C14: Free allocation does not exceed scenario calls | D14: ='Funnel & cost'!D33 -> 0 | E14: ='Funnel & cost'!D31 -> 310 | F14: =IF(D14<=E14,"PASS","FAIL") -> PASS | G14: Cap allocated events at calls.
B15: QA-10 | C15: Raw density/saturation warm calls are zero | D15: =SUMIFS('Raw validation'!$I:$I,'Raw validation'!$E:$E,"Warm") -> 0 | E15: 0 | F15: =IF(D15=E15,"PASS","FAIL") -> PASS | G15: Review cache repeat evidence.
B16: QA-11 | C16: Spatial restriction results outside rectangle | D16: =SUMIFS('Raw validation'!$O:$O,'Raw validation'!$E:$E,"Restriction") -> 0 | E16: 0 | F16: =IF(D16=E16,"PASS","FAIL") -> PASS | G16: Review restriction test import.
B17: QA-12 | C17: Source lookup for price returns published value | D17: =Assumptions!C27 -> 35 | E17: 35 | F17: =IF(D17=E17,"PASS","FAIL") -> PASS | G17: Review source key/reference.
B18: QA-13 | C18: Outcome tracker remains separate from the planning model | D18: =COUNT('Outcome plan'!C6:C23) -> 0 | E18: 0 | F18: =IF(D18=0,"PASS","REVIEW") -> PASS | G18: When populated, confirm campaign dates and ID before reporting KPIs.
B19: QA-14 | C19: Market-run ledger matches the operator-recorded Google Cloud count | D19: =SUMIFS('Raw validation'!$I:$I,'Raw validation'!$B:$B,"Market grid",'Raw validation'!$E:$E,"Cold",'Raw validation'!$R:$R,"run-20260904-024050-et") -> 224 | E19: =INDEX('Source register'!$D$6:$D$31,MATCH("cloud_request_count",'Source register'!$B$6:$B$31,0)) -> 224 | F19: =IF(D19=E19,"PASS","FAIL") -> PASS | G19: Reconcile run ledger and Cloud Console export.
B20: QA-15 | C20: Market run remains within the approved call cap | D20: =SUMIFS('Raw validation'!$I:$I,'Raw validation'!$B:$B,"Market grid",'Raw validation'!$E:$E,"Cold",'Raw validation'!$R:$R,"run-20260904-024050-et") -> 224 | E20: =INDEX('Source register'!$D$6:$D$31,MATCH("market_run_call_cap",'Source register'!$B$6:$B$31,0)) -> 225 | F20: =IF(D20<=E20,"PASS","FAIL") -> PASS | G20: Confirm the pre-run cap and call ledger.
B21: MODEL STATUS
B23: What PASS means | C23: The model reconciles to its inputs. Record actual campaign outcomes separately on Outcome plan.
